OktmoParser/__init__.py
OktmoParser/oktmo.py
oktmoparser-1.3.2.dist-info/METADATA
oktmoparser-1.3.2.dist-info/WHEEL
oktmoparser-1.3.2.dist-info/top_level.txt
oktmoparser-1.3.2.dist-info/RECORD
