Metadata-Version: 2.1
Name: oktmoparser
Version: 1.3.2
Summary: Simple and useful parser that helps you get actual All-Russian Classifier of Municipal Territories (OKTMO)
Home-page: https://github.com/letimvkocmoc/oktmo-parser
Author: letimvkocmoc
Author-email: letimvkocmoc@gmail.com
Project-URL: GitGub, https://github.com/letimvkocmoc
Keywords: oktmo parser municipal territory classifier
Classifier: Programming Language :: Python :: 3.12
Classifier: License :: OSI Approved :: MIT License
Classifier: Operating System :: OS Independent
Requires-Dist: requests
